robotpy_sphinx/__init__.py
robotpy_sphinx/all.py
robotpy_sphinx/download_and_install.py
robotpy_sphinx/pybind11_fixer.py
robotpy_sphinx/regen.py
robotpy_sphinx/sidebar.py
robotpy_sphinx/utils.py
robotpy_sphinx_plugin-0.2.5.dist-info/METADATA
robotpy_sphinx_plugin-0.2.5.dist-info/WHEEL
robotpy_sphinx_plugin-0.2.5.dist-info/top_level.txt
robotpy_sphinx_plugin-0.2.5.dist-info/RECORD
