Metadata-Version: 2.1
Name: robotpy-sphinx-plugin
Version: 0.2.5
Summary: Common Sphinx tooling for RobotPy projects
Home-page: https://github.com/robotpy/robotpy-sphinx-plugin
Author: Dustin Spicuzza
Author-email: robotpy@googlegroups.com
License: BSD-3-Clause
Platform: UNKNOWN
Classifier: Development Status :: 5 - Production/Stable
Classifier: Intended Audience :: Developers
Classifier: License :: OSI Approved :: BSD License
Classifier: Programming Language :: Python :: 3 :: Only
Classifier: Topic :: Software Development
Requires-Python: >=3.6
Requires-Dist: setuptools >=43
Requires-Dist: setuptools-scm >=6
Requires-Dist: sphinx-autodoc-typehints
Requires-Dist: sphinx-automodapi
Requires-Dist: requests
Requires-Dist: packaging
Requires-Dist: toml
